<?xml version="1.0" encoding="UTF-8"?>
<mule xmlns="http://www.mulesoft.org/schema/mule/core" xmlns:apikit="http://www.mulesoft.org/schema/mule/mule-apikit" xmlns:db="http://www.mulesoft.org/schema/mule/db" xmlns:doc="http://www.mulesoft.org/schema/mule/documentation" xmlns:ee="http://www.mulesoft.org/schema/mule/ee/core" xmlns:http="http://www.mulesoft.org/schema/mule/http" xmlns:xsi="http://www.w3.org/2001/XMLSchema-instance" xsi:schemaLocation="http://www.mulesoft.org/schema/mule/core http://www.mulesoft.org/schema/mule/core/current/mule.xsd http://www.mulesoft.org/schema/mule/http http://www.mulesoft.org/schema/mule/http/current/mule-http.xsd http://www.mulesoft.org/schema/mule/mule-apikit http://www.mulesoft.org/schema/mule/mule-apikit/current/mule-apikit.xsd  http://www.mulesoft.org/schema/mule/ee/core http://www.mulesoft.org/schema/mule/ee/core/current/mule-ee.xsd http://www.mulesoft.org/schema/mule/db http://www.mulesoft.org/schema/mule/db/current/mule-db.xsd">
    <http:listener-config name="payment-httpListenerConfig">
        <http:listener-connection host="0.0.0.0" port="8010" />
    </http:listener-config>
    <apikit:config name="payment-config" raml="payment.raml" outboundHeadersMapName="outboundHeaders" httpStatusVarName="httpStatus" />
    <db:config name="Database_Config_P" doc:name="Database Config" doc:id="ab41ca15-8cff-4774-ac09-1a487f8f9937">
        <db:oracle-connection host="192.168.56.105" user="ndadmin" password="password" serviceName="xe" />
    </db:config>
    <http:request-config name="HTTP_Request_configuration1" doc:name="HTTP Request configuration" doc:id="77b60221-b8c3-498a-b63f-2238672dcd32" >
		<http:request-connection host="localhost" port="8082" />
	</http:request-config>
	<flow name="payment-main">
        <http:listener config-ref="payment-httpListenerConfig" path="/api/*">
            <http:response statusCode="#[vars.httpStatus default 200]">
                <http:headers>#[vars.outboundHeaders default {}]</http:headers>
            </http:response>
            <http:error-response statusCode="#[vars.httpStatus default 500]">
                <http:body>#[payload]</http:body>
                <http:headers>#[vars.outboundHeaders default {}]</http:headers>
            </http:error-response>
        </http:listener>
        <apikit:router config-ref="payment-config" />
        <error-handler>
            <on-error-propagate type="APIKIT:BAD_REQUEST">
                <ee:transform xsi:schemaLocation="http://www.mulesoft.org/schema/mule/ee/core http://www.mulesoft.org/schema/mule/ee/core/current/mule-ee.xsd">
                    <ee:message>
                        <ee:set-payload><![CDATA[%dw 2.0
output application/json
---
{message: "Bad request"}]]></ee:set-payload>
                    </ee:message>
                    <ee:variables>
                        <ee:set-variable variableName="httpStatus">400</ee:set-variable>
                    </ee:variables>
                </ee:transform>
            </on-error-propagate>
            <on-error-propagate type="APIKIT:NOT_FOUND">
                <ee:transform xsi:schemaLocation="http://www.mulesoft.org/schema/mule/ee/core http://www.mulesoft.org/schema/mule/ee/core/current/mule-ee.xsd">
                    <ee:message>
                        <ee:set-payload><![CDATA[%dw 2.0
output application/json
---
{message: "Resource not found"}]]></ee:set-payload>
                    </ee:message>
                    <ee:variables>
                        <ee:set-variable variableName="httpStatus">404</ee:set-variable>
                    </ee:variables>
                </ee:transform>
            </on-error-propagate>
            <on-error-propagate type="APIKIT:METHOD_NOT_ALLOWED">
                <ee:transform xsi:schemaLocation="http://www.mulesoft.org/schema/mule/ee/core http://www.mulesoft.org/schema/mule/ee/core/current/mule-ee.xsd">
                    <ee:message>
                        <ee:set-payload><![CDATA[%dw 2.0
output application/json
---
{message: "Method not allowed"}]]></ee:set-payload>
                    </ee:message>
                    <ee:variables>
                        <ee:set-variable variableName="httpStatus">405</ee:set-variable>
                    </ee:variables>
                </ee:transform>
            </on-error-propagate>
            <on-error-propagate type="APIKIT:NOT_ACCEPTABLE">
                <ee:transform xsi:schemaLocation="http://www.mulesoft.org/schema/mule/ee/core http://www.mulesoft.org/schema/mule/ee/core/current/mule-ee.xsd">
                    <ee:message>
                        <ee:set-payload><![CDATA[%dw 2.0
output application/json
---
{message: "Not acceptable"}]]></ee:set-payload>
                    </ee:message>
                    <ee:variables>
                        <ee:set-variable variableName="httpStatus">406</ee:set-variable>
                    </ee:variables>
                </ee:transform>
            </on-error-propagate>
            <on-error-propagate type="APIKIT:UNSUPPORTED_MEDIA_TYPE">
                <ee:transform xsi:schemaLocation="http://www.mulesoft.org/schema/mule/ee/core http://www.mulesoft.org/schema/mule/ee/core/current/mule-ee.xsd">
                    <ee:message>
                        <ee:set-payload><![CDATA[%dw 2.0
output application/json
---
{message: "Unsupported media type"}]]></ee:set-payload>
                    </ee:message>
                    <ee:variables>
                        <ee:set-variable variableName="httpStatus">415</ee:set-variable>
                    </ee:variables>
                </ee:transform>
            </on-error-propagate>
            <on-error-propagate type="APIKIT:NOT_IMPLEMENTED">
                <ee:transform xsi:schemaLocation="http://www.mulesoft.org/schema/mule/ee/core http://www.mulesoft.org/schema/mule/ee/core/current/mule-ee.xsd">
                    <ee:message>
                        <ee:set-payload><![CDATA[%dw 2.0
output application/json
---
{message: "Not Implemented"}]]></ee:set-payload>
                    </ee:message>
                    <ee:variables>
                        <ee:set-variable variableName="httpStatus">501</ee:set-variable>
                    </ee:variables>
                </ee:transform>
            </on-error-propagate>
        </error-handler>
    </flow>
    <flow name="payment-console">
        <http:listener config-ref="payment-httpListenerConfig" path="/console/*">
            <http:response statusCode="#[vars.httpStatus default 200]">
                <http:headers>#[vars.outboundHeaders default {}]</http:headers>
            </http:response>
            <http:error-response statusCode="#[vars.httpStatus default 500]">
                <http:body>#[payload]</http:body>
                <http:headers>#[vars.outboundHeaders default {}]</http:headers>
            </http:error-response>
        </http:listener>
        <apikit:console config-ref="payment-config" />
        <error-handler>
            <on-error-propagate type="APIKIT:NOT_FOUND">
                <ee:transform xsi:schemaLocation="http://www.mulesoft.org/schema/mule/ee/core http://www.mulesoft.org/schema/mule/ee/core/current/mule-ee.xsd">
                    <ee:message>
                        <ee:set-payload><![CDATA[%dw 2.0
output application/json
---
{message: "Resource not found"}]]></ee:set-payload>
                    </ee:message>
                    <ee:variables>
                        <ee:set-variable variableName="httpStatus">404</ee:set-variable>
                    </ee:variables>
                </ee:transform>
            </on-error-propagate>
        </error-handler>
    </flow>
    <flow name="post:\payment\accountid:payment-config">
        <logger level="INFO" doc:name="Logger" doc:id="3e17994e-a0fd-4cc3-8b8c-ac1680f15d45" message="get:\payment\cardNumber\(cNumber):payment-config" />
        <set-variable value="#[%dw 2.0 output application/java --- payload.accountid as String]" doc:name="accountID" doc:id="058f0810-f6f3-4563-b6ed-d0ab4311ce73" variableName="accountID" />
        <db:select doc:id="2d50c395-42a5-45f9-aa65-0b0a5ac49f5a" config-ref="Database_Config_P">
            <db:sql>select * from transactions where card_number=:accountid</db:sql>
            <db:input-parameters><![CDATA[#[%dw 2.0
output application/java
---
{
	accountid: vars.accountid
}]]]></db:input-parameters>
        </db:select>
        <ee:transform doc:name="Transform Message" doc:id="72113efb-8cf2-4480-8c94-888b10c6831f">
            <ee:message>
                <ee:set-payload><![CDATA[%dw 2.0
output application/json
---
payload]]></ee:set-payload>
            </ee:message>
        </ee:transform>
    </flow>
    <flow name="get:\payment:payment-config">
        <logger level="INFO" doc:name="Logger" doc:id="644ea93d-7b31-4f72-a591-d7d044190adc" message="get:\payment:payment-config" />
        <db:select doc:name="Select" doc:id="e067e206-78ce-464f-89ac-1e2ec4d6ed83" config-ref="Database_Config_P">
            <db:sql>select * from transactions</db:sql>
        </db:select>
        <ee:transform xsi:schemaLocation=" http://www.mulesoft.org/schema/mule/db http://www.mulesoft.org/schema/mule/db/current/mule-db.xsd  http://www.mulesoft.org/schema/mule/mule-apikit http://www.mulesoft.org/schema/mule/mule-apikit/current/mule-apikit.xsd  http://www.mulesoft.org/schema/mule/http http://www.mulesoft.org/schema/mule/http/current/mule-http.xsd http://www.mulesoft.org/schema/mule/ee/core http://www.mulesoft.org/schema/mule/ee/core/current/mule-ee.xsd" doc:id="cf052914-3cf2-432a-a2c2-44b7c1b0a3fd">
            <ee:message>
                <ee:set-payload><![CDATA[%dw 2.0
output application/json
---
payload]]></ee:set-payload>
            </ee:message>
        </ee:transform>
    </flow>
    <flow name="post:\payment:payment-config">
        <logger level="INFO" doc:name="Logger" doc:id="9672a9ba-194c-432a-86a3-332d839a6f24" message="post:\payment:payment-config" />
        <set-variable value="#[payload.cardnumber]" doc:name="Card Number" doc:id="34f84b7e-b368-4361-94aa-3238397878fc" variableName="CardNumber" />
        <set-variable value='#[payload.amount]' doc:name="ammount" doc:id="29873578-2715-4822-8419-7c61d5eac6a5" variableName="ammount" />
        <db:insert doc:name="Insert" doc:id="7c90d002-3bfd-42f7-beef-c9d9c6e127e5" config-ref="Database_Config_P">
            <db:sql>insert into transactions (transaction_id, transaction_date, amount, card_number, trans_source, trans_description, status, trans_type) values (:id, :tdate, :amount, :card_number, :trans_source, :trans_description, :status, :trans_type)</db:sql>
            <db:input-parameters><![CDATA[#[%dw 2.0
output application/java
---
{
	id: payload.transactionID,
	tdate: payload.date as Date,
	amount: payload.amount as Number,
	card_number: payload.cardnumber,
	trans_source: payload.source,
	trans_description: payload.description,
	status: payload.status,
	trans_type: payload.Type
}]]]></db:input-parameters>
        </db:insert>
		<http:request method="PUT" doc:name="Request" doc:id="ab13d947-2ad5-49d4-8788-292a1772aee1" config-ref="HTTP_Request_configuration1" url="http://localhost:8082/api/creditcards/payment">
			<http:body ><![CDATA[#[{
  "cardNumber": vars.CardNumber,
  "balance": vars.ammount
}]]]></http:body>
		</http:request>
    </flow>
</mule>